[
  {
    "id": "life",
    "name": "生活日常",
    "icon": "☕",
    "color": "bg-sun",
    "questions": [
      {
        "question": "周末最想干嘛？",
        "options": [
          "睡到自然醒",
          "打游戏",
          "吃大餐",
          "逛街购物",
          "发呆放空"
        ]
      },
      {
        "question": "最爱的夜宵是？",
        "options": [
          "烧烤串串",
          "泡面加蛋",
          "麻辣烫",
          "炸鸡啤酒",
          "小龙虾"
        ]
      },
      {
        "question": "早上几点起床？",
        "options": [
          "六点晨型人",
          "七点刚刚好",
          "八点踩点",
          "九点勉强起",
          "中午才起"
        ]
      },
      {
        "question": "健身房还是沙发？",
        "options": [
          "燃烧我的卡",
          "沙发永远神",
          "三天打鱼型",
          "办卡吃灰中",
          "沙发仰卧起坐"
        ]
      },
      {
        "question": "最常点的外卖？",
        "options": [
          "黄焖鸡米饭",
          "沙县小吃",
          "兰州拉面",
          "麻辣香锅",
          "汉堡薯条"
        ]
      },
      {
        "question": "奶茶选什么糖？",
        "options": [
          "全糖才快乐",
          "半糖刚刚好",
          "三分糖健康",
          "无糖要了命",
          "不喝奶茶"
        ]
      },
      {
        "question": "理想早餐是？",
        "options": [
          "油条豆浆",
          "包子稀饭",
          "面包牛奶",
          "煎饼果子",
          "干脆不吃"
        ]
      },
      {
        "question": "夏天续命神器？",
        "options": [
          "空调西瓜",
          "冰镇可乐",
          "游泳池泡着",
          "电风扇猛吹",
          "心静自然凉"
        ]
      },
      {
        "question": "钱先花在哪？",
        "options": [
          "吃吃喝喝",
          "数码产品",
          "衣服鞋包",
          "游戏氪金",
          "存起来吃灰"
        ]
      },
      {
        "question": "晚上几点睡？",
        "options": [
          "十点养生局",
          "十一点正常",
          "十二点标配",
          "凌晨一点起",
          "通宵选手"
        ]
      },
      {
        "question": "出行首选方式？",
        "options": [
          "地铁挤挤",
          "打车舒服",
          "共享单车",
          "自己开车",
          "两条腿走"
        ]
      },
      {
        "question": "最受不了的家务？",
        "options": [
          "洗碗刷锅",
          "拖地扫地",
          "洗衣服",
          "做饭炒菜",
          "倒垃圾"
        ]
      },
      {
        "question": "手机先看什么？",
        "options": [
          "刷朋友圈",
          "看抖音",
          "回微信",
          "刷微博",
          "打游戏"
        ]
      },
      {
        "question": "一周洗几次头？",
        "options": [
          "每天必洗",
          "隔天一次",
          "三天一次",
          "一周两次",
          "能不洗不洗"
        ]
      },
      {
        "question": "理想客厅长啥样？",
        "options": [
          "大电视沙发",
          "投影仪影院",
          "书架满墙",
          "绿植环绕",
          "极简风"
        ]
      }
    ]
  },
  {
    "id": "love",
    "name": "恋爱心动",
    "icon": "💕",
    "color": "bg-coral-light",
    "questions": [
      {
        "question": "第一次约会去哪？",
        "options": [
          "电影院",
          "咖啡厅",
          "游乐园",
          "高档餐厅",
          "夜市逛街"
        ]
      },
      {
        "question": "理想纪念日礼物？",
        "options": [
          "鲜花巧克力",
          "限量首饰",
          "手写情书",
          "惊喜旅行",
          "红包转账"
        ]
      },
      {
        "question": "吃醋了怎么办？",
        "options": [
          "直接质问",
          "冷战沉默",
          "疯狂暗示",
          "假装没事",
          "反过来气ta"
        ]
      },
      {
        "question": "暗恋怎么表白？",
        "options": [
          "当面直说",
          "发微信表白",
          "写情书",
          "让朋友传话",
          "打死不说"
        ]
      },
      {
        "question": "吵架谁先低头？",
        "options": [
          "男方先认错",
          "女方先认错",
          "谁错谁认",
          "都不低头",
          "第三方调停"
        ]
      },
      {
        "question": "情侣头像选啥？",
        "options": [
          "卡通萌系",
          "真人合照",
          "动漫CP",
          "搞怪表情包",
          "不用情侣头"
        ]
      },
      {
        "question": "理想约会时长？",
        "options": [
          "半天刚好",
          "一整天",
          "吃个饭就行",
          "通宵达旦",
          "看心情定"
        ]
      },
      {
        "question": "最甜的称呼？",
        "options": [
          "宝贝儿",
          "老公老婆",
          "小名昵称",
          "哥哥妹妹",
          "直呼大名"
        ]
      },
      {
        "question": "情人节怎么过？",
        "options": [
          "浪漫晚餐",
          "在家做饭",
          "看场电影",
          "送花送礼",
          "假装不知道"
        ]
      },
      {
        "question": "异地恋能撑多久？",
        "options": [
          "三个月内",
          "半年左右",
          "一年坚持",
          "两年磨炼",
          "直接结婚"
        ]
      },
      {
        "question": "最想收到的消息？",
        "options": [
          "想你了",
          "我爱你",
          "今晚见",
          "给你买东西",
          "转你红包"
        ]
      },
      {
        "question": "约会迟到怎么办？",
        "options": [
          "等十分钟",
          "催一下",
          "直接走人",
          "也迟到报复",
          "无所谓等"
        ]
      },
      {
        "question": "情侣装怎么搭？",
        "options": [
          "同款同色",
          "同款不同色",
          "元素呼应",
          "一起搞怪",
          "不穿情侣装"
        ]
      },
      {
        "question": "最受不了对象？",
        "options": [
          "沉迷游戏",
          "手机不离手",
          "吃醋粘人",
          "邋遢不收拾",
          "说话不算数"
        ]
      },
      {
        "question": "求婚方式选啥？",
        "options": [
          "当众下跪",
          "旅行惊喜",
          "家里温馨",
          "视频剪辑",
          "直接领证"
        ]
      }
    ]
  },
  {
    "id": "funny",
    "name": "搞笑脑洞",
    "icon": "🤪",
    "color": "bg-mint",
    "questions": [
      {
        "question": "丧尸来了带什么？",
        "options": [
          "啤酒花生",
          "平底锅",
          "物理课本",
          "带女朋友",
          "笔记本电脑"
        ]
      },
      {
        "question": "超能力选哪个？",
        "options": [
          "隐身穿墙",
          "瞬间移动",
          "读心术",
          "时间停止",
          "吃不胖"
        ]
      },
      {
        "question": "最离谱口头禅？",
        "options": [
          "卧槽",
          "笑死",
          "绝了",
          "麻了",
          "蚌埠住了"
        ]
      },
      {
        "question": "外星人来了咋办？",
        "options": [
          "跑为上策",
          "拍照发圈",
          "请ta吃饭",
          "装没看见",
          "拉去展览"
        ]
      },
      {
        "question": "变成动物选啥？",
        "options": [
          "国宝熊猫",
          "池塘乌龟",
          "家里橘猫",
          "草原狮子",
          "天上麻雀"
        ]
      },
      {
        "question": "末日最后一天？",
        "options": [
          "吃遍美食",
          "表白心意",
          "睡个够",
          "疯狂剁手",
          "宅家追剧"
        ]
      },
      {
        "question": "穿越回古代？",
        "options": [
          "当皇帝",
          "做生意",
          "考状元",
          "仗剑天涯",
          "种田养老"
        ]
      },
      {
        "question": "鬼魂敲门咋办？",
        "options": [
          "给ta开门",
          "装死",
          "念经驱鬼",
          "拍照留念",
          "请ta喝茶"
        ]
      },
      {
        "question": "必须删一个APP？",
        "options": [
          "微信",
          "抖音",
          "微博",
          "王者荣耀",
          "淘宝"
        ]
      },
      {
        "question": "时光机去哪？",
        "options": [
          "看恐龙",
          "未来世界",
          "唐朝盛世",
          "自己童年",
          "明朝看看"
        ]
      },
      {
        "question": "一辈子只吃一样？",
        "options": [
          "火锅",
          "炸鸡",
          "奶茶",
          "米饭",
          "泡面"
        ]
      },
      {
        "question": "突然暴富干嘛？",
        "options": [
          "环球旅行",
          "买房收租",
          "投资创业",
          "吃喝玩乐",
          "全部捐了"
        ]
      },
      {
        "question": "变成食物选啥？",
        "options": [
          "麻辣火锅",
          "北京烤鸭",
          "小龙虾",
          "寿司",
          "臭豆腐"
        ]
      },
      {
        "question": "最想要的奇葩技能？",
        "options": [
          "永不秃头",
          "秒睡技能",
          "吃不胖体质",
          "十秒记忆",
          "自带BGM"
        ]
      },
      {
        "question": "重活一次选啥？",
        "options": [
          "还是普通人",
          "当富二代",
          "做明星",
          "当科学家",
          "继续这样"
        ]
      }
    ]
  },
  {
    "id": "work",
    "name": "职场社畜",
    "icon": "💼",
    "color": "bg-cream-dark",
    "questions": [
      {
        "question": "摸鱼首选？",
        "options": [
          "刷手机",
          "带薪拉屎",
          "假装敲键盘",
          "看小说",
          "和同事聊天"
        ]
      },
      {
        "question": "最烦的会议？",
        "options": [
          "早会洗脑",
          "周报总结",
          "头脑风暴",
          "领导训话",
          "跨部门扯皮"
        ]
      },
      {
        "question": "加班夜宵选啥？",
        "options": [
          "泡面",
          "烧烤",
          "外卖炸鸡",
          "便利店饭团",
          "不吃减肥"
        ]
      },
      {
        "question": "老板叫你咋办？",
        "options": [
          "装没听见",
          "立刻过去",
          "拖五分钟",
          "问什么事",
          "先回个收到"
        ]
      },
      {
        "question": "理想薪资？",
        "options": [
          "月入一万",
          "月入三万",
          "月入五万",
          "年入百万",
          "财务自由"
        ]
      },
      {
        "question": "同事借钱咋办？",
        "options": [
          "直接拒绝",
          "借一点点",
          "装穷哭惨",
          "问清用途",
          "看关系定"
        ]
      },
      {
        "question": "周一心情？",
        "options": [
          "想请假",
          "困到不行",
          "斗志满满",
          "算计周末",
          "已经麻木"
        ]
      },
      {
        "question": "团建最想去？",
        "options": [
          "KTV嗨唱",
          "农家乐",
          "海边度假",
          "密室逃脱",
          "不去最好"
        ]
      },
      {
        "question": "工位必备？",
        "options": [
          "零食储备",
          "保温杯",
          "靠垫护腰",
          "小风扇",
          "拖鞋一双"
        ]
      },
      {
        "question": "下班后干嘛？",
        "options": [
          "直接回家",
          "约朋友吃饭",
          "健身房撸铁",
          "加班继续",
          "躺平刷手机"
        ]
      },
      {
        "question": "离职原因？",
        "options": [
          "钱少事多",
          "老板太傻",
          "同事内卷",
          "没发展",
          "想换城市"
        ]
      },
      {
        "question": "年会表演啥？",
        "options": [
          "唱首歌",
          "跳支舞",
          "说段相声",
          "装病不上",
          "被迫主持"
        ]
      },
      {
        "question": "上班穿搭？",
        "options": [
          "正装出席",
          "休闲舒适",
          "格子衫标配",
          "拖鞋短裤",
          "工装工牌"
        ]
      },
      {
        "question": "食堂最难吃？",
        "options": [
          "隔夜剩菜",
          "菜没味道",
          "油太大",
          "全是素",
          "米饭夹生"
        ]
      },
      {
        "question": "升职靠什么？",
        "options": [
          "拼命干活",
          "拍马屁",
          "靠关系",
          "运气好",
          "跳槽最快"
        ]
      }
    ]
  }
]
